baldrick/__init__.py
baldrick/config.py
baldrick/conftest.py
baldrick/utils.py
baldrick/blueprints/__init__.py
baldrick/blueprints/circleci.py
baldrick/blueprints/github.py
baldrick/blueprints/tests/__init__.py
baldrick/blueprints/tests/test_circleci.py
baldrick/blueprints/tests/test_github.py
baldrick/github/__init__.py
baldrick/github/github_api.py
baldrick/github/github_auth.py
baldrick/github/tests/__init__.py
baldrick/github/tests/test_github_api.py
baldrick/github/tests/test_github_auth.py
baldrick/plugins/__init__.py
baldrick/plugins/circleci_artifacts.py
baldrick/plugins/github_milestones.py
baldrick/plugins/github_pull_requests.py
baldrick/plugins/github_towncrier_changelog.py
baldrick/plugins/tests/__init__.py
baldrick/plugins/tests/test_circleci_artifacts.py
baldrick/plugins/tests/test_github_milestones.py
baldrick/plugins/tests/test_github_pull_requests.py
baldrick/plugins/tests/test_github_towncrier_changelog.py
baldrick/scripts/__init__.py
baldrick/scripts/stale_issues.py
baldrick/scripts/stale_pull_requests.py
baldrick/scripts/tests/__init__.py
baldrick/scripts/tests/test_stale_issues.py
baldrick/scripts/tests/test_stale_pull_requests.py
baldrick/tests/__init__.py
baldrick/tests/test_config.py
baldrick/tests/test_utils.py
baldrick-0.2.dist-info/METADATA
baldrick-0.2.dist-info/RECORD
baldrick-0.2.dist-info/WHEEL
baldrick-0.2.dist-info/entry_points.txt
baldrick-0.2.dist-info/top_level.txt
