Metadata-Version: 2.1
Name: baldrick
Version: 0.2
Summary: baldrick: a cunning plan for GitHub bots
Home-page: https://github.com/astrofrog/baldrick
Author: Stuart Mumford and Thomas Robitaille
Author-email: thomas.robitaille@gmail.com
License: UNKNOWN
Platform: UNKNOWN
Provides-Extra: test
Provides-Extra: docs
Requires-Dist: flask
Requires-Dist: pyjwt
Requires-Dist: requests
Requires-Dist: python-dateutil
Requires-Dist: cryptography
Requires-Dist: humanize
Requires-Dist: towncrier
Requires-Dist: toml
Requires-Dist: ttldict
Provides-Extra: docs
Requires-Dist: sphinx; extra == 'docs'
Requires-Dist: sphinx-automodapi; extra == 'docs'
Provides-Extra: test
Requires-Dist: pytest (<3.7,>=3.5); extra == 'test'
Requires-Dist: pytest-flake8; extra == 'test'
Requires-Dist: pytest-cov; extra == 'test'
Requires-Dist: codecov; extra == 'test'
Requires-Dist: towncrier; extra == 'test'
